{
  "db_name": "PostgreSQL",
  "query": "SELECT date,\n                      CASE WHEN $2::boolean THEN low_foil ELSE low END as \"low\",\n                      CASE WHEN $2::boolean THEN trend_foil ELSE trend END as \"trend\",\n                      CASE WHEN $2::boolean THEN avg_foil ELSE avg END as \"avg\"\n               FROM cardmarket_price\n               WHERE id_produit = $1 AND date >= $3 AND date <= $4\n               ORDER BY date",
  "describe": {
    "columns": [
      {
        "ordinal": 0,
        "name": "date",
        "type_info": "Date",
        "origin": {
          "Table": {
            "table": "cardmarket_price",
            "name": "date"
          }
        }
      },
      {
        "ordinal": 1,
        "name": "low",
        "type_info": "Int4",
        "origin": "Expression"
      },
      {
        "ordinal": 2,
        "name": "trend",
        "type_info": "Int4",
        "origin": "Expression"
      },
      {
        "ordinal": 3,
        "name": "avg",
        "type_info": "Int4",
        "origin": "Expression"
      }
    ],
    "parameters": {
      "Left": [
        "Int4",
        "Bool",
        "Date",
        "Date"
      ]
    },
    "nullable": [
      false,
      null,
      null,
      null
    ]
  },
  "hash": "301b12717389f4fdd422698506174db1e8c4564b0db92bf8a83ba6d8ab2dbea1"
}
